roebots/__init__.py
roebots/colors.py
roebots/csv_writer.py
roebots/job_runner.py
roebots/ros_serializer.py
roebots/ros_visualizer.py
roebots/utils.py
roebots-2025.10.10.dist-info/licenses/LICENSE
roebots-2025.10.10.dist-info/METADATA
roebots-2025.10.10.dist-info/WHEEL
roebots-2025.10.10.dist-info/entry_points.txt
roebots-2025.10.10.dist-info/top_level.txt
roebots-2025.10.10.dist-info/RECORD
