Metadata-Version: 2.4
Name: roebots
Version: 2025.10.10
Summary: A package of some utils for doing robotics and ML.
Home-page: http://pypi.python.org/pypi/roebots/
Author: Adrian Röfer
Author-email: Adrian Röfer <aroefer@cs.uni-freiburg.de>
License-Expression: GPL-3.0-or-later
Project-URL: Homepage, https://github.com/ARoefer/roebots
Project-URL: Issues, https://github.com/ARoefer/roebots/issues
Classifier: Programming Language :: Python :: 3
Classifier: Operating System :: OS Independent
Requires-Python: >=3.10
License-File: LICENSE
Requires-Dist: numpy>=1.26.4
Requires-Dist: scipy>=1.14.0
Requires-Dist: textual
Dynamic: author
Dynamic: home-page
Dynamic: license-file
